helyos_agent_sdk/__init__.py
helyos_agent_sdk/client.py
helyos_agent_sdk/connector.py
helyos_agent_sdk/crypto.py
helyos_agent_sdk/database_connector.py
helyos_agent_sdk/exceptions.py
helyos_agent_sdk/models.py
helyos_agent_sdk/mqtt_client.py
helyos_agent_sdk/summary_request.py
helyos_agent_sdk/utils.py
helyos_agent_sdk-0.8.1.dist-info/LICENSE
helyos_agent_sdk-0.8.1.dist-info/METADATA
helyos_agent_sdk-0.8.1.dist-info/WHEEL
helyos_agent_sdk-0.8.1.dist-info/RECORD
