Metadata-Version: 2.1
Name: helyos_agent_sdk
Version: 0.8.1
Summary: Package encloses methods and data definitions that facilitate the connection of agents in the helyOS framework.
Home-page: https://helyosframework.org
Keywords: autonomous driving,helyos,agent,robot
Author: Carlos Viol Barbosa , Julius Kolb
Requires-Python: >=3.7,<4.0
Classifier: Environment :: Console
Classifier: Operating System :: OS Independent
Classifier: Programming Language :: Python :: 3
Classifier: Programming Language :: Python :: 3.7
Classifier: Programming Language :: Python :: 3.8
Classifier: Programming Language :: Python :: 3.9
Classifier: Programming Language :: Python :: 3.10
Classifier: Programming Language :: Python :: 3.11
Classifier: Programming Language :: Python :: 3.12
Classifier: Programming Language :: Python :: 3.13
Classifier: Topic :: Software Development :: Build Tools
Classifier: Topic :: Software Development :: Libraries :: Python Modules
Requires-Dist: cryptography (>=41.0.3,<42.0.0)
Requires-Dist: dataclasses-json (>=0.5.7,<0.6.0)
Requires-Dist: paho-mqtt (>=1.6.1,<2.0.0)
Requires-Dist: pika (>=1.3.1,<2.0.0)
Requires-Dist: pycryptodome (>=3.15.0,<4.0.0)
Requires-Dist: requests (>=2.31.0,<3.0.0) ; sys_platform == "win32" or sys_platform == "linux"
Project-URL: Documentation, https://helyosframework.github.io/helyos_agent_sdk/
Project-URL: Repository, https://github.com/helyOSFramework/helyos_agent_sdk
